MANIFEST.in
README.md
setup.py
PYXInput.egg-info/PKG-INFO
PYXInput.egg-info/SOURCES.txt
PYXInput.egg-info/dependency_links.txt
PYXInput.egg-info/top_level.txt
pyxinput/__init__.py
pyxinput/read_state.py
pyxinput/virtual_controller.py
pyxinput.egg-info/PKG-INFO
pyxinput.egg-info/SOURCES.txt
pyxinput.egg-info/dependency_links.txt
pyxinput.egg-info/top_level.txt
pyxinput/ScpVBus-x64/ScpVBus.inf
pyxinput/ScpVBus-x64/ScpVBus.sys
pyxinput/ScpVBus-x64/WdfCoinstaller01009.dll
pyxinput/ScpVBus-x64/devcon.exe
pyxinput/ScpVBus-x64/install.bat
pyxinput/ScpVBus-x64/readme.txt
pyxinput/ScpVBus-x64/scpvbus.cat
pyxinput/ScpVBus-x64/uninstall.bat
pyxinput/ScpVBus-x86/ScpVBus.inf
pyxinput/ScpVBus-x86/ScpVBus.sys
pyxinput/ScpVBus-x86/WdfCoinstaller01009.dll
pyxinput/ScpVBus-x86/devcon.exe
pyxinput/ScpVBus-x86/scpvbus.cat
pyxinput/vXboxInterface-x64/SCPUser.exe
pyxinput/vXboxInterface-x64/msvcp120.dll
pyxinput/vXboxInterface-x64/msvcr120.dll
pyxinput/vXboxInterface-x64/readme.txt
pyxinput/vXboxInterface-x64/vXboxInterface.dll
pyxinput/vXboxInterface-x86/SCPUser.exe
pyxinput/vXboxInterface-x86/msvcp120.dll
pyxinput/vXboxInterface-x86/msvcr120.dll
pyxinput/vXboxInterface-x86/readme.txt
pyxinput/vXboxInterface-x86/vXboxInterface.dll