Metadata-Version: 1.1
Name: pyxinput
Version: 0.9.0
Summary: Python Implmenentation of vXbox and XInput DLL
Home-page: https://github.com/bayangan1991/PYXInput
Author: Ryan Barnes (@bayangan1991)
Author-email: ryan.bayangan@gmail.com
License: MIT
Keywords: pygta5 virtual xbox controller xinput
Platform: UNKNOWN
Classifier: Development Status :: 4 - Beta
Classifier: Intended Audience :: Developers
Classifier: Topic :: Software Development :: Build Tools
Classifier: License :: OSI Approved :: MIT License
Classifier: Programming Language :: Python :: 3
Classifier: Programming Language :: Python :: 3.3
Classifier: Programming Language :: Python :: 3.4
Classifier: Programming Language :: Python :: 3.5
